.DS_Store
bin_classifier_ensemble.py
categoric2numeric.py
similarity.py
tmgsimple.py
toolbox_02450.py
toolbox_extended.py
ml02450-1.0.0.dist-info/METADATA
ml02450-1.0.0.dist-info/RECORD
ml02450-1.0.0.dist-info/WHEEL
ml02450-1.0.0.dist-info/top_level.txt
