Metadata-Version: 2.1
Name: ml02450
Version: 1.0.0
Summary: A library for the machine learning and data mining course at DTU
Home-page: https://github.com/thomasnilsson/ml02450
Author: tnni
Author-email: tnni@dtu.dk
License: MIT
Platform: UNKNOWN
